demo_package/__init__.py
demo_package/hello.py
demo_package_tea_redcat_001-0.0.1.dist-info/LICENSE
demo_package_tea_redcat_001-0.0.1.dist-info/METADATA
demo_package_tea_redcat_001-0.0.1.dist-info/WHEEL
demo_package_tea_redcat_001-0.0.1.dist-info/top_level.txt
demo_package_tea_redcat_001-0.0.1.dist-info/RECORD
