Metadata-Version: 2.1
Name: demo_package_tea_redcat_001
Version: 0.0.1
Summary: 这是一个用于演示如何上传到PyPI的测试项目。
Home-page: https://github.com/yourusername/demo_package
Author: steven
Author-email: ccs9214221@gmail.com
License: MIT License
Classifier: Programming Language :: Python :: 3
Classifier: License :: OSI Approved :: MIT License
Classifier: Operating System :: OS Independent
Requires-Python: >=3.6
License-File: LICENSE
